[ 
  {
    "ingredient": "ACHIOTE SEEDS",
    "pairings": [
      "beef",
      "chicken",
      "chiles",
      "fish",
      "game birds",
      "garlic",
      "mexican cuisine*",
      "oil",
      "pork*",
      "shellfish"
    ]
  },

  {
    "ingredient": "AFGHAN CUISINE",
    "pairings": [
      "almonds",
      "barley",
      "breads*",
      "cardamom",
      "chile pepper",
      "cinnamon",
      "cloves",
      "coriander",
      "cucumber",
      "cumin",
      "dill",
      "fennel",
      "fruits (dried)",
      "ginger",
      "grapes",
      "kebabs",
      "lamb",
      "mint",
      "mushrooms",
      "nuts (almonds)",
      "pasta*",
      "rice* (basmati)",
      "sesame",
      "tomatoes and tomato sauce",
      "turmeric",
      "yogurt*"
    ]
  },

  {
    "ingredient": "AFRICAN CUISINE (SOUTH)",
    "pairings": [
      "beans",
      "carrots",
      "chile peppers",
      "cinnamon",
      "cloves",
      "fenugreek",
      "garlic",
      "ginger",
      "lamb",
      "onions",
      "peas",
      "pumpkin",
      "stews",
      "tomatoes",
      "turmeric"
    ]
  },

  {
    "ingredient": "ALMONDS",
    "pairings": [
      "amaretto",
      "anise, esp. green",
      "apples",
      "apricots*",
      "beans",
      "blackberries",
      "brandy",
      "butter, unsalted**",
      "butterscotch",
      "caramel*",
      "cardamom",
      "cayenne",
      "cheese: goat, manchego, ricotta",
      "cherries, esp. sour",
      "chicken",
      "chocolate  (dark, milk)**",
      "chocolate, white",
      "cinnamon",
      "coconut*",
      "coffee*",
      "cornmeal",
      "corn syrup",
      "crab",
      "cranberries",
      "cream**",
      "cream cheese",
      "crème fraîche",
      "crust: pastry, pie",
      "currants",
      "figs*",
      "fish",
      "french pastries",
      "fruits, most",
      "garlic",
      "grapes",
      "greek cuisine",
      "greens, salad",
      "hazelnuts*",
      "honey**",
      "ice cream",
      "indian cuisine",
      "italian sauces",
      "lamb",
      "lavender",
      "lemon: juice, zest*",
      "liqueurs, fruit (including orange)",
      "mascarpone",
      "mediterranean cuisine",
      "mexican beverages and mole sauces",
      "milk, sweetened condensed",
      "molasses",
      "moroccan cuisine",
      "nectarines",
      "oats",
      "olive oil*",
      "olives",
      "orange: juice, zest*",
      "paprika",
      "passion fruit",
      "peaches",
      "pears",
      "pecans",
      "pepper, ground",
      "pine nuts",
      "plums",
      "praline",
      "prunes",
      "quince",
      "raisins, esp. white",
      "raspberries",
      "rhubarb",
      "rice",
      "rosemary",
      "rum",
      "salt: kosher, sea*",
      "shellfish",
      "sherry",
      "spanish cuisine, esp. sauces",
      "strawberries",
      "sugar (brown, white)",
      "tea",
      "turkish cuisine",
      "vanilla**",
      "walnuts"
    ]
  },

  {
    "ingredient": "AMARETTO",
    "pairings": [
      "almonds",
      "apricots",
      "butter",
      "cherries",
      "chocolate",
      "coffee",
      "cream",
      "hazelnuts",
      "italian cuisine",
      "peaches",
      "pork",
      "sugar"
    ]
  },

  {
    "ingredient": "ANCHOVIES",
    "pairings": [
      "almonds*",
      "basil",
      "beans, green",
      "bell peppers, esp. roasted",
      "capers*",
      "carrots",
      "cauliflower",
      "celery",
      "cheese: manchego, mozzarella, parmesan*",
      "chives",
      "eggs, hard-boiled*",
      "fennel",
      "garlic**",
      "lemon, juice*",
      "lobster",
      "mayonnaise*",
      "mediterranean cuisine",
      "mustard (e.g., dijon)",
      "nectarines",
      "olive oil**",
      "olives (e.g., black, green, niçoise)*",
      "onions",
      "orange, zest",
      "parsley, flat-leaf*",
      "pasta*",
      "pepper: black, white*",
      "peppers, piquillo",
      "pizza",
      "potatoes",
      "puttanesca sauce (key ingredient)",
      "red pepper flakes",
      "romaine lettuce",
      "rosemary",
      "salads, esp. caesar (key ingredient)",
      "salmon",
      "salt: kosher, sea*",
      "shallots",
      "sherry, PX",
      "tapenade (key ingredient)",
      "thyme",
      "tomatoes",
      "tuna",
      "vinegar: champagne, red wine, sherry*"
    ]
  },

  {
    "ingredient": "ANGELICA",
    "pairings": [
      "almonds*",
      "anise",
      "apricots*",
      "candy",
      "cream and ice cream*",
      "custards",
      "desserts*",
      "fish",
      "fruits",
      "ginger: fresh, candied*",
      "hazelnuts",
      "juniper berries",
      "lavender*",
      "lemon balm",
      "liqueurs",
      "mushrooms",
      "nutmeg",
      "oranges*",
      "pepper, black",
      "plums",
      "RHUBARB***",
      "salads",
      "shellfish",
      "strawberries*"
    ]
  },


  {
    "ingredient": "APPLE",
    "pairings": [
      "apple cider or juice*",
      "applejack*",
      "apricots: dried, jam, puree*",
      "armagnac",
      "bacon",
      "bay leaf",
      "beef",
      "blackberries",
      "bourbon",
      "brandy, esp. apple*",
      "brioche",
      "butter, unsalted**",
      "butterscotch",
      "cabbage, red",
      "calvados**",
      "caramel**",
      "cardamom",
      "celery",
      "celery root",
      "cheese: camembert, cheddar, goat, gruyère*",
      "cherries: dried, fresh",
      "chestnuts",
      "chicken",
      "chives",
      "cider",
      "cinnamon***",
      "cloves*",
      "cognac*",
      "cointreau",
      "coriander",
      "cranberries",
      "cream and ice cream**",
      "crème anglaise (sauce)",
      "crème fraîche",
      "crust: pastry, pie",
      "cumin",
      "currants, esp. black, and currant jelly",
      "curry powder",
      "custards*",
      "dates",
      "duck",
      "eggplant",
      "fennel",
      "french cuisine, esp. from normandy",
      "frisée",
      "ginger*",
      "goose",
      "hazelnuts",
      "honey, esp. chestnut, wildflower*",
      "horseradish",
      "ice cream",
      "kirsch*",
      "lavender",
      "lemon: juice, zest**",
      "lemon thyme",
      "lychees",
      "madeira*",
      "maple syrup",
      "mayonnaise",
      "meringue",
      "molasses",
      "mustard",
      "nutmeg*",
      "nuts",
      "oatmeal and oats",
      "oil: canola, hazelnut, walnut",
      "olive oil",
      "onions, esp. green, red",
      "orange: juice, zest",
      "parsley",
      "peanuts and peanut butter",
      "pears",
      "pecans*",
      "pepper, black",
      "pies",
      "pineapple",
      "pine nuts*",
      "pistachios",
      "plums",
      "pomegranates",
      "pork*",
      "poultry",
      "prunes",
      "puff pastry",
      "pumpkin",
      "quince",
      "raisins, esp. seedless, white*",
      "rhubarb",
      "rice and rice pudding",
      "rosemary",
      "rum: dark, light**",
      "salads: fruit, green",
      "salt, kosher",
      "sauerkraut",
      "sherry*",
      "soups",
      "sour cream",
      "star anise",
      "sugar: brown, white**",
      "sweet potatoes*",
      "tarragon",
      "tarts",
      "thyme",
      "vanilla*",
      "verjus",
      "vermouth*",
      "vinegar: apple cider, raspberry",
      "walnuts**",
      "wine: red, dry white",
      "yogurt"
    ]
  },

  {
    "ingredient": "APRICOTS",
    "pairings": [
      "almonds**",
      "amaretto",
      "anise",
      "apples*",
      "apricot brandy",
      "bananas",
      "blackberries",
      "blueberries",
      "brandy",
      "butter, unsalted",
      "caramel",
      "cardamom*",
      "cayenne",
      "cheese (e.g., brie, reblochon, ricotta)",
      "cheesecake",
      "cherries*",
      "chicken",
      "chocolate, white",
      "cinnamon*",
      "coconut",
      "coffee and espresso",
      "cognac",
      "coriander",
      "cranberries*",
      "cream and ice cream**",
      "crème anglaise",
      "custards (e.g., crème brûlée)*",
      "duck",
      "foie gras",
      "game",
      "garlic",
      "ginger*",
      "hazelnuts",
      "honey",
      "ice cream, esp. vanilla",
      "kirsch*",
      "lamb",
      "lemon: juice, zest**",
      "lemon verbena",
      "liqueurs: apricot, nut",
      "maple syrup",
      "mascarpone",
      "mediterranean cuisine",
      "meringue",
      "middle eastern stews",
      "mint (garnish)",
      "moroccan cuisine",
      "nectarines",
      "nutmeg",
      "nuts",
      "oats and oatmeal",
      "onions, esp. yellow",
      "orange: juice, zest*",
      "orange liqueur",
      "peaches",
      "pepper, black*",
      "pineapple",
      "pine nuts",
      "pistachios*",
      "plums",
      "pork",
      "poultry",
      "praline",
      "prunes",
      "raisins",
      "raspberries",
      "rice pudding",
      "rosemary",
      "rum",
      "saffron",
      "salads, esp. fruit, green",
      "sauternes",
      "sour cream",
      "strawberries",
      "sugar: brown, white**",
      "tea: apple, apricot, earl grey",
      "vanilla***",
      "vinegar, red wine",
      "walnuts",
      "wine: sweet, white",
      "yogurt"
    ]
  },

  {
    "ingredient": "ARTICHOKES",
    "pairings": [
      "aioli",
      "anchovies*",
      "arugula",
      "bacon",
      "basil",
      "bay leaf*",
      "beans, fava",
      "beets",
      "bell peppers, esp. roasted",
      "bread crumbs*",
      "butter*",
      "capers",
      "carrots",
      "cashews",
      "celery",
      "cheese: emmental, goat, gruyère, parmesan*",
      "chervil",
      "chicken",
      "chives",
      "coriander",
      "cream",
      "crème fraîche",
      "eggs: yolk, hard-boiled",
      "french cuisine",
      "garlic**",
      "grapefruit",
      "ham (e.g., serrano)",
      "hazelnuts",
      "hollandaise sauce",
      "italian cuisine",
      "leeks",
      "lemon: confit, juice, zest**",
      "lobster",
      "mayonnaise*",
      "mediterranean cuisine",
      "mint**",
      "moroccan cuisine",
      "mushrooms",
      "mustard, dijon",
      "nuts: cashews, hazelnuts, walnuts",
      "oil: hazelnut, peanut",
      "olive oil**",
      "olives: black, niçoise",
      "onions, esp. sweet and yellow**",
      "orange",
      "pancetta",
      "parsley, flat-leaf**",
      "pepper: black, white**",
      "pesto",
      "piquillo peppers",
      "potatoes",
      "prosciutto",
      "radicchio",
      "red pepper flakes",
      "rice",
      "risotto",
      "rosemary",
      "saffron",
      "sage",
      "salads",
      "salt, kosher**",
      "savory",
      "shallots",
      "shellfish (e.g., crab)",
      "sherry, dry",
      "shrimp",
      "soy sauce",
      "spanish cuisine",
      "spinach",
      "stock, chicken",
      "sugar (pinch)",
      "tapenade",
      "tarragon, fresh",
      "thyme, fresh**",
      "tomatoes**",
      "truffles, black",
      "tuna",
      "vinaigrette",
      "vinegar: balsamic, rice, sherry, white wine",
      "walnuts",
      "wine, dry white**",
      "yogurt"
    ]
  }
  
  



]
